{
    "name": "Roerbak tonijn met groente",
    "slug": "roerbak-tonijn-met-groente",
    "category": "dinner",
    "ingredients": [
        "2 blikjes tonijn",
        "Prei",
        "Courgette",
        "Paddestoelen",
        "Ui",
        "Knoflook",
        "2 eieren",
        "2 pepertjes",
        "Citroen",
        "Limoen",
        "Augurk",
        "Optioneel: gember",
        "Komkommer voor erbij"
    ],
    "steps": [
        "Snijd de prei, courgette, paddestoelen, ui en knoflook in kleine stukjes.",
        "Verhit een pan met een beetje olie en fruit de ui en knoflook tot ze geurig zijn.",
        "Voeg de prei, courgette en paddestoelen toe. Roerbak totdat de groenten zacht beginnen te worden.",
        "Laat de tonijn uitlekken en voeg deze toe aan de pan. Meng goed door de groenten.",
        "Kluts de eieren in een kom en giet deze over het mengsel. Roerbak tot het ei is gestold.",
        "Snijd de pepertjes fijn en voeg deze toe naar smaak.",
        "Knijp sap van een halve citroen en een halve limoen over het gerecht.",
        "Snijd augurk in kleine stukjes en voeg deze toe voor extra smaak.",
        "Als gewenst, rasp een beetje verse gember en meng dit door het gerecht.",
        "Serveer met plakjes komkommer als frisse bijgerecht."
    ],
    "source": "N/A"
}
